NextPClogic.v
`timescale 1ns/1ps

module NextPClogic(
    output reg [63:0] NextPC,
    input  [63:0] CurrentPC,
    input  [63:0] SignExtImm64,
    input         Branch,
    input         ALUZero,
    input         Uncondbranch
);

always @(*) begin
    // Default: sequential next PC
    NextPC = CurrentPC + 64'd4;

    // Conditional branch
    if (Branch && ALUZero) begin
        NextPC = CurrentPC + SignExtImm64;
    end

    // Unconditional branch overrides everything
    if (Uncondbranch) begin
        NextPC = CurrentPC + SignExtImm64;
    end
end

endmodule

DataMemory.v
`timescale 1ns / 1ps

module DataMemory (
    output wire [63:0] ReadData,
    input  wire [63:0] Address,   
    input  wire [63:0] WriteData,
    input  wire        MemoryRead,
    input  wire        MemoryWrite,
    input  wire        Clock
);

    // 64-bit words, indexed by Address[10:3] (8-byte aligned)
    reg [63:0] mem [0:255];
    integer i;

    // Initialization for Program
    initial begin
        mem[0] = 64'd1;                        // at address 0x00
        mem[1] = 64'd10;                       // at address 0x08
        mem[2] = 64'd5;                        // at address 0x10
        mem[3] = 64'h0FFBEA7DEADBEEFF;         // at address 0x18
        for (i = 4; i < 256; i = i + 1)
            mem[i] = 64'd0;
    end

    // Compute 8-byte word index
    wire [7:0] idx = Address[10:3];

    // Combinational read (single-cycle)
    assign ReadData = MemoryRead ? mem[idx] : 64'd0;

    // Sequential write
    always @(posedge Clock) begin
        if (MemoryWrite)
            mem[idx] <= WriteData;
    end


endmodule

ALU.v
`timescale 1ns/1ps

`define AND    4'b0000
`define OR     4'b0001
`define ADD    4'b0010
`define SUB    4'b0110
`define PassB  4'b0111

module ALU(
    output reg [63:0] BusW,
    input      [63:0] BusA,
    input      [63:0] BusB,
    input      [3:0]  ALUCtrl,
    output reg        Zero
);

always @(*) begin
    case(ALUCtrl)
        `AND:    BusW = BusA & BusB;
        `OR:     BusW = BusA | BusB;
        `ADD:    BusW = BusA + BusB;
        `SUB:    BusW = BusA - BusB;
        `PassB:  BusW = BusB;        // For CBZ / PassB
        default: BusW = 64'b0;
    endcase

    // Zero flag must reflect BusW after operation
    if (BusW == 64'b0)
        Zero = 1'b1;
    else
        Zero = 1'b0;
end

endmodule

mux2to1_64.v
`timescale 1ns / 1ps

module mux2to1_64( // originally mux2to1_8
    input wire [63:0] in0,
    input wire [63:0] in1,
    input wire       sel,
    output reg [63:0] out
    );
    always @(*) begin
        out = sel ? in1 : in0;
    end
endmodule

SignExtender.v
`timescale 1ns/1ps

// Sign extension mode encodings
`define Itype   2'b00
`define Dtype   2'b01
`define CBtype  2'b10
`define Btype   2'b11

module SignExtender(
    output reg [63:0] SignExOut,
    input  wire [25:0] Instruction,
    input  wire [1:0]  SignOp,
    input  wire        IsMovz
);
    reg [1:0]  hw;
    reg [15:0] imm16;

    always @(*) begin
        // Default values to prevent latch inference
        hw        = 2'b00;
        imm16     = 16'd0;
        SignExOut = 64'd0;

        if (IsMovz) begin
            // ============================
            // MOVZ: IM-format (zero-extend + shift by hw*16)
            // ============================
            imm16 = Instruction[20:5];
            hw    = Instruction[22:21];
            SignExOut = {48'd0, imm16} << (hw * 16);
        end
        else begin
            case (SignOp)
                // ============================
                // I-type (ADDI, SUBI)
                // ============================
                `Itype: begin
                    SignExOut = {{52{Instruction[21]}}, Instruction[21:10]};
                end

                // ============================
                // D-type (LDUR, STUR)
                // ============================
                `Dtype: begin
                    SignExOut = {{55{Instruction[20]}}, Instruction[20:12]};
                end

                // ============================
                // CB-type (CBZ)
                // imm19 = bits [23:5], shift left 2
                // ============================
                `CBtype: begin
                    SignExOut = {{43{Instruction[23]}}, Instruction[23:5], 2'b00};
                end

                // ============================
                // B-type (B)
                // imm26 = bits [25:0], shift left 2
                // ============================
                `Btype: begin
                    SignExOut = {{36{Instruction[25]}}, Instruction[25:0], 2'b00};
                end

                default: begin
                    SignExOut = 64'd0;
                end
            endcase
        end
    end
endmodule

RegisterFile.v
`timescale 1ns / 1ps

module RegisterFile(
    output wire [63:0] BusA,
    output wire [63:0] BusB,
    input  wire [63:0] BusW,
    input  wire [4:0]  RA,
    input  wire [4:0]  RB,
    input  wire [4:0]  RW,
    input  wire        RegWr,
    input  wire        Clk
);

    // ARMv8 has 32 64-bit registers (X0-X30 general, X31 = XZR)
    reg [63:0] registers [0:30]; // Registers X0-X30
    integer i;

    // Previous-cycle write capture (for 1-cycle-late bypass)
    reg [4:0]  last_rw;
    reg [63:0] last_data;
    reg        last_write_valid;

    // =========================
    // Initialization
    // =========================
    initial begin
        for (i = 0; i < 31; i = i + 1)
            registers[i] = 64'd0;
        last_rw = 5'd0;
        last_data = 64'd0;
        last_write_valid = 1'b0;
    end

    // =========================
    // Sequential write and capture
    // =========================
    always @(posedge Clk) begin
        if (RegWr && (RW != 5'd31)) begin
            registers[RW] <= BusW;
            last_rw <= RW;
            last_data <= BusW;
            last_write_valid <= 1'b1;
        end else begin
            last_write_valid <= 1'b0;
        end
    end

    // =========================
    // Safe register read helper (function)
    // =========================
    function [63:0] safe_read;
        input [4:0] addr;
        begin
            if (addr == 5'd31)              // XZR always 0
                safe_read = 64'd0;
            else if (addr > 5'd30)          // Out of range (shouldn't happen)
                safe_read = 64'dX;
            else
                safe_read = registers[addr]; // Normal read
        end
    endfunction

    // =========================
    // One-cycle-late bypass
    // =========================
    wire [63:0] readA, readB;

    assign readA = (last_write_valid && (RA == last_rw) && (RA != 5'd31)) ? last_data : safe_read(RA);
    assign readB = (last_write_valid && (RB == last_rw) && (RB != 5'd31)) ? last_data : safe_read(RB);

    // =========================
    // Outputs (with delay)
    // =========================
    assign #3 BusA = readA;
    assign #3 BusB = readB;

endmodule

SC_Control.v
`timescale 1ns / 1ps

// =========================
// Opcode Definitions
// =========================
`define OPCODE_ANDREG 11'b10001010000
`define OPCODE_ORRREG 11'b10101010000
`define OPCODE_ADDREG 11'b10001011000
`define OPCODE_SUBREG 11'b11001011000

`define OPCODE_ADDIMM 11'b1001000100?
`define OPCODE_SUBIMM 11'b1101000100?

`define OPCODE_MOVZ   11'b110100101??

`define OPCODE_B      11'b000101?????
`define OPCODE_CBZ    11'b10110100???
`define OPCODE_LDUR   11'b11111000010
`define OPCODE_STUR   11'b11111000000

// =========================
// SC_Control
// =========================
module SC_Control(
    output reg IsMovz,
    output reg       Reg2Loc,
    output reg       ALUSrc,
    output reg       MemtoReg,
    output reg       RegWrite,
    output reg       MemRead,
    output reg       MemWrite,
    output reg       Branch,
    output reg       Uncondbranch,
    output reg [3:0] ALUOp,
    output reg [1:0] SignOp,
    input  wire [10:0] opcode
);

    // ALUOp encodings :
    // 4'b0000 = AND, 4'b0001 = ORR, 4'b0010 = ADD, 4'b0110 = SUB, 4'b0111 = PassB
    // 2'b00 = I-type (ADD/SUB imm), 2'b01 = D-type (LDUR/STUR),
    // 2'b10 = CB-type (CBZ),        2'b11 = B-type (B)
    
    always @(*) begin
        IsMovz = 1'b0;
        // -------- Safe defaults (undefined opcodes -> all zeros) --------
        Reg2Loc      = 1'b0;
        ALUSrc       = 1'b0;
        MemtoReg     = 1'b0;
        RegWrite     = 1'b0;
        MemRead      = 1'b0;
        MemWrite     = 1'b0;
        Branch       = 1'b0;
        Uncondbranch = 1'b0;
        ALUOp        = 4'b0000;
        SignOp       = 2'b00;

        casez (opcode)
            // =========================
            // Load / Store
            // =========================
            `OPCODE_LDUR: begin
                ALUSrc       = 1'b1;         // base + offset
                MemtoReg     = 1'b1;         // write memory data to reg
                RegWrite     = 1'b1;
                MemRead      = 1'b1;
                ALUOp        = 4'b0010;      // ADD
                SignOp       = 2'b01;        // D-type immediate
            end

            `OPCODE_STUR: begin
                Reg2Loc      = 1'b1;         // use Rt field as second read reg
                ALUSrc       = 1'b1;         // base + offset
                MemWrite     = 1'b1;
                ALUOp        = 4'b0010;      // ADD
                SignOp       = 2'b01;        // D-type immediate
            end

            // =========================
            // R-type (register) ops
            // =========================
            `OPCODE_ADDREG: begin
                RegWrite     = 1'b1;
                ALUOp        = 4'b0010;      // ADD
            end

            `OPCODE_SUBREG: begin
                RegWrite     = 1'b1;
                ALUOp        = 4'b0110;      // SUB
            end

            `OPCODE_ANDREG: begin
                RegWrite     = 1'b1;
                ALUOp        = 4'b0000;      // AND
            end

            `OPCODE_ORRREG: begin
                RegWrite     = 1'b1;
                ALUOp        = 4'b0001;      // ORR
            end

            // =========================
            // I-type (immediate) ops
            // =========================
            `OPCODE_ADDIMM: begin
                ALUSrc       = 1'b1;         // use immediate
                RegWrite     = 1'b1;
                ALUOp        = 4'b0010;      // ADD
                SignOp       = 2'b00;        // I-type immediate
            end

            `OPCODE_SUBIMM: begin
                ALUSrc       = 1'b1;         // use immediate
                RegWrite     = 1'b1;
                ALUOp        = 4'b0110;      // SUB
                SignOp       = 2'b00;        // I-type immediate
            end

            // =========================
            // MOVZ (move wide with zero)
            // =========================
            `OPCODE_MOVZ: begin
                IsMovz = 1'b1;
                ALUSrc       = 1'b1;         // use immediate (zero-extended/shifted in datapath)
                RegWrite     = 1'b1;
                ALUOp        = 4'b0111;      // PassB (write immediate directly)
                SignOp       = 2'b00;
            end

            // =========================
            // Branches
            // =========================
            `OPCODE_CBZ: begin
                Reg2Loc      = 1'b1;         // read Rt to test against zero
                Branch       = 1'b1;         // conditional branch enable
                ALUOp        = 4'b0111;      // PassB (forward register value to zero-check)
                SignOp       = 2'b10;        // CB-type immediate
            end

            `OPCODE_B: begin
                Uncondbranch = 1'b1;         // unconditional branch
                // ALU not used for target calc in this simple SC; PC update logic uses SignExt
                SignOp       = 2'b11;        // B-type immediate
            end

            default: begin
                // keep safe defaults (all zeros)
            end
        endcase
    end
endmodule

InstructionMemory.v
`timescale 1ns / 1ps

module InstructionMemory(
    output reg [31:0] Data,
    input  wire [63:0] Address
);
    parameter T_rd = 20;
    parameter MemSize = 40;

    always @(*) begin
        case (Address)
            // =========================
            // Test Program 1 (spec)
            // =========================
            64'h000: Data = 32'hF84003E9; // LDUR X9,  [XZR, 0x0]
            64'h004: Data = 32'hF84083EA; // LDUR X10, [XZR, 0x8]
            64'h008: Data = 32'hF84103EB; // LDUR X11, [XZR, 0x10]
            64'h00C: Data = 32'hF84183EC; // LDUR X12, [XZR, 0x18]
            64'h010: Data = 32'hF84203ED; // LDUR X13, [XZR, 0x20]
            64'h014: Data = 32'hAA0B014A; // ORR X10, X10, X11
            64'h018: Data = 32'h8A0A018C; // AND X12, X12, X10
            64'h01C: Data = 32'hB400008C; // CBZ X12, end
            64'h020: Data = 32'h8B0901AD; // ADD X13, X13, X9
            64'h024: Data = 32'hCB09018C; // SUB X12, X12, X9
            64'h028: Data = 32'h17FFFFFD; // B loop
            64'h02C: Data = 32'hF80203ED; // STUR X13, [XZR, 0x20]
            64'h030: Data = 32'hF84203ED; // LDUR X13, [XZR, 0x20]

            // =========================
            // Test Program 2 (MOVZ build + store/load)
            // =========================
            64'h034: Data = 32'hD2E24689; // MOVZ X9,  0x1234 << 48
            64'h038: Data = 32'hD2CACF0A; // MOVZ X10, 0x5678 << 32
            64'h03C: Data = 32'hAA0A0129; // ORR X9, X9, X10
            64'h040: Data = 32'hD2B3578A; // MOVZ X10, 0x9ABC << 16
            64'h044: Data = 32'hAA0A0129; // ORR X9, X9, X10
            64'h048: Data = 32'hD29BDE0A; // MOVZ X10, 0xDEF0 << 0
            64'h04C: Data = 32'hAA0A0129; // ORR X9, X9, X10
            64'h050: Data = 32'hF80283E9; // STUR X9,  [XZR, 0x28]
            64'h054: Data = 32'hF84283EA; // LDUR X10, [XZR, 0x28]

            default: Data = 32'h00000000;
        endcase
    end
endmodule

SingleCycleProc.v
`timescale 1ns / 1ps

module SingleCycleProc(
    input              reset,        // Active High
    input      [63:0]  startpc,      // Starting PC
    output reg [63:0]  currentpc,    // Current PC
    output     [63:0]  MemtoRegOut,  // Output of MemtoReg mux
    input              CLK           // Clock
);

   // =========================
   // Internal wires
   // =========================
   wire [63:0] nextpc;
   wire [31:0] instruction;

   // Instruction fields
   wire [4:0]  Rt;     // Destination register
   wire [4:0]  Rn;     // First source (base)
   wire [4:0]  Rm;     // Second source
   wire [4:0]  RBsel;  // Second register after Reg2Loc mux
   wire [10:0] opcode;

   // Control signals
   wire        Reg2Loc;
   wire        ALUSrc;
   wire        MemtoReg;
   wire        RegWrite;
   wire        MemRead;
   wire        MemWrite;
   wire        Branch;
   wire        Uncondbranch;
   wire [3:0]  ALUOp;
   wire [1:0]  SignOp;

   // Datapath signals
   wire [63:0] regoutA;
   wire [63:0] regoutB;
   wire [63:0] aluout;
   wire [63:0] readdata;
   wire [63:0] SignExOut;
   wire [63:0] alu_in_b;
   wire        zero;

   // =========================
   // Instruction decoding
   // =========================
   assign Rt     = instruction[4:0];
   assign Rn     = instruction[9:5];
   assign Rm     = instruction[20:16];
   assign opcode = instruction[31:21];
   assign RBsel  = Reg2Loc ? Rt : Rm; // select based on instruction type

   // =========================
   // Instruction Memory
   // =========================
   InstructionMemory imem(
      .Data(instruction),
      .Address(currentpc)
   );

   // =========================
   // Control Unit
   // =========================
    wire IsMovz;
    
    SC_Control control(
       .Reg2Loc(Reg2Loc),
       .ALUSrc(ALUSrc),
       .MemtoReg(MemtoReg),
       .RegWrite(RegWrite),
       .MemRead(MemRead),
       .MemWrite(MemWrite),
       .Branch(Branch),
       .Uncondbranch(Uncondbranch),
       .ALUOp(ALUOp),
       .SignOp(SignOp),
       .IsMovz(IsMovz),           // <-- new connection
       .opcode(opcode)
    );

   // =========================
   // Register File
   // =========================
   RegisterFile rf(
      .BusA (regoutA),
      .BusB (regoutB),
      .BusW (MemtoRegOut),
      .RA   (Rn),
      .RB   (RBsel),
      .RW   (Rt),
      .RegWr(RegWrite),
      .Clk  (CLK)
   );

   // =========================
   // Sign Extender
   // =========================
    SignExtender sext(
       .SignExOut (SignExOut),
       .Instruction(instruction[25:0]),
       .SignOp(SignOp),
       .IsMovz(IsMovz)            // <-- new port
    );

   // =========================
   // ALU Input Mux (ALUSrc)
   // =========================
   mux2to1_64 alu_b_mux(
      .in0 (regoutB),
      .in1 (SignExOut),
      .sel (ALUSrc),
      .out (alu_in_b)
   );

   // =========================
   // ALU
   // =========================
   ALU alu(
      .BusW   (aluout),
      .BusA   (regoutA),
      .BusB   (alu_in_b),
      .ALUCtrl(ALUOp),
      .Zero   (zero)
   );

   // =========================
   // Data Memory
   // =========================
   DataMemory dmem(
      .ReadData   (readdata),
      .Address    (aluout),
      .WriteData  (regoutB),
      .MemoryRead (MemRead),
      .MemoryWrite(MemWrite),
      .Clock      (CLK)
   );

   // =========================
   // MemtoReg Mux (Writeback)
   // =========================
   assign MemtoRegOut = MemtoReg ? readdata : aluout;

   // =========================
   // Next PC Logic
   // =========================
   NextPClogic npcl(
      .NextPC       (nextpc),
      .CurrentPC    (currentpc),
      .SignExtImm64 (SignExOut),
      .Branch       (Branch),
      .ALUZero      (zero),
      .Uncondbranch (Uncondbranch)
   );

   // =========================
   // Program Counter Update
   // =========================
   always @(posedge CLK) begin
      if (reset)
         currentpc <= #3 startpc;
      else
         currentpc <= #3 nextpc;
   end

endmodule

trace.vcd
$version Generated by VerilatedVcd $end
$timescale 1ps $end
 $scope module TOP $end
  $var wire 1 -! reset $end
  $var wire 64 .! startpc [63:0] $end
  $var wire 64 0! currentpc [63:0] $end
  $var wire 64 2! MemtoRegOut [63:0] $end
  $var wire 1 4! CLK $end
  $scope module SingleCycleProc $end
   $var wire 1 -! reset $end
   $var wire 64 .! startpc [63:0] $end
   $var wire 64 0! currentpc [63:0] $end
   $var wire 64 2! MemtoRegOut [63:0] $end
   $var wire 1 4! CLK $end
   $var wire 64 % nextpc [63:0] $end
   $var wire 32 ' instruction [31:0] $end
   $var wire 5 ( Rt [4:0] $end
   $var wire 5 ) Rn [4:0] $end
   $var wire 5 * Rm [4:0] $end
   $var wire 5 + RBsel [4:0] $end
   $var wire 11 , opcode [10:0] $end
   $var wire 1 - Reg2Loc $end
   $var wire 1 . ALUSrc $end
   $var wire 1 / MemtoReg $end
   $var wire 1 0 RegWrite $end
   $var wire 1 1 MemRead $end
   $var wire 1 2 MemWrite $end
   $var wire 1 3 Branch $end
   $var wire 1 4 Uncondbranch $end
   $var wire 4 5 ALUOp [3:0] $end
   $var wire 2 6 SignOp [1:0] $end
   $var wire 64 7 regoutA [63:0] $end
   $var wire 64 9 regoutB [63:0] $end
   $var wire 64 ; aluout [63:0] $end
   $var wire 64 = readdata [63:0] $end
   $var wire 64 ? SignExOut [63:0] $end
   $var wire 64 A alu_in_b [63:0] $end
   $var wire 1 C zero $end
   $var wire 1 D IsMovz $end
   $scope module alu $end
    $var wire 64 ; BusW [63:0] $end
    $var wire 64 7 BusA [63:0] $end
    $var wire 64 A BusB [63:0] $end
    $var wire 4 5 ALUCtrl [3:0] $end
    $var wire 1 C Zero $end
   $upscope $end
   $scope module alu_b_mux $end
    $var wire 64 9 in0 [63:0] $end
    $var wire 64 ? in1 [63:0] $end
    $var wire 1 . sel $end
    $var wire 64 A out [63:0] $end
   $upscope $end
   $scope module control $end
    $var wire 1 D IsMovz $end
    $var wire 1 - Reg2Loc $end
    $var wire 1 . ALUSrc $end
    $var wire 1 / MemtoReg $end
    $var wire 1 0 RegWrite $end
    $var wire 1 1 MemRead $end
    $var wire 1 2 MemWrite $end
    $var wire 1 3 Branch $end
    $var wire 1 4 Uncondbranch $end
    $var wire 4 5 ALUOp [3:0] $end
    $var wire 2 6 SignOp [1:0] $end
    $var wire 11 , opcode [10:0] $end
   $upscope $end
   $scope module dmem $end
    $var wire 64 = ReadData [63:0] $end
    $var wire 64 ; Address [63:0] $end
    $var wire 64 9 WriteData [63:0] $end
    $var wire 1 1 MemoryRead $end
    $var wire 1 2 MemoryWrite $end
    $var wire 1 4! Clock $end
    $var wire 32 # i [31:0] $end
    $var wire 8 E idx [7:0] $end
   $upscope $end
   $scope module imem $end
    $var wire 32 ' Data [31:0] $end
    $var wire 64 0! Address [63:0] $end
    $var wire 32 5! T_rd [31:0] $end
    $var wire 32 6! MemSize [31:0] $end
   $upscope $end
   $scope module npcl $end
    $var wire 64 % NextPC [63:0] $end
    $var wire 64 0! CurrentPC [63:0] $end
    $var wire 64 ? SignExtImm64 [63:0] $end
    $var wire 1 3 Branch $end
    $var wire 1 C ALUZero $end
    $var wire 1 4 Uncondbranch $end
   $upscope $end
   $scope module rf $end
    $var wire 64 7 BusA [63:0] $end
    $var wire 64 9 BusB [63:0] $end
    $var wire 64 2! BusW [63:0] $end
    $var wire 5 ) RA [4:0] $end
    $var wire 5 + RB [4:0] $end
    $var wire 5 ( RW [4:0] $end
    $var wire 1 0 RegWr $end
    $var wire 1 4! Clk $end
    $var wire 64 F registers[0] [63:0] $end
    $var wire 64 H registers[1] [63:0] $end
    $var wire 64 J registers[2] [63:0] $end
    $var wire 64 L registers[3] [63:0] $end
    $var wire 64 N registers[4] [63:0] $end
    $var wire 64 P registers[5] [63:0] $end
    $var wire 64 R registers[6] [63:0] $end
    $var wire 64 T registers[7] [63:0] $end
    $var wire 64 V registers[8] [63:0] $end
    $var wire 64 X registers[9] [63:0] $end
    $var wire 64 Z registers[10] [63:0] $end
    $var wire 64 \ registers[11] [63:0] $end
    $var wire 64 ^ registers[12] [63:0] $end
    $var wire 64 ` registers[13] [63:0] $end
    $var wire 64 b registers[14] [63:0] $end
    $var wire 64 d registers[15] [63:0] $end
    $var wire 64 f registers[16] [63:0] $end
    $var wire 64 h registers[17] [63:0] $end
    $var wire 64 j registers[18] [63:0] $end
    $var wire 64 l registers[19] [63:0] $end
    $var wire 64 n registers[20] [63:0] $end
    $var wire 64 p registers[21] [63:0] $end
    $var wire 64 r registers[22] [63:0] $end
    $var wire 64 t registers[23] [63:0] $end
    $var wire 64 v registers[24] [63:0] $end
    $var wire 64 x registers[25] [63:0] $end
    $var wire 64 z registers[26] [63:0] $end
    $var wire 64 | registers[27] [63:0] $end
    $var wire 64 ~ registers[28] [63:0] $end
    $var wire 64 "! registers[29] [63:0] $end
    $var wire 64 $! registers[30] [63:0] $end
    $var wire 32 $ i [31:0] $end
    $var wire 5 &! last_rw [4:0] $end
    $var wire 64 '! last_data [63:0] $end
    $var wire 1 )! last_write_valid $end
    $var wire 64 7 readA [63:0] $end
    $var wire 64 9 readB [63:0] $end
   $upscope $end
   $scope module sext $end
    $var wire 64 ? SignExOut [63:0] $end
    $var wire 26 *! Instruction [25:0] $end
    $var wire 2 6 SignOp [1:0] $end
    $var wire 1 D IsMovz $end
    $var wire 2 +! hw [1:0] $end
    $var wire 16 ,! imm16 [15:0] $end
   $upscope $end
  $upscope $end
 $upscope $end
$enddefinitions $end


#0
b00000000000000000000000100000000 #
b00000000000000000000000000011111 $
b0000000000000000000000000000000000000000000000000000000000000100 %
b11111000010000000000001111101001 '
b01001 (
b11111 )
b00000 *
b00000 +
b11111000010 ,
0-
1.
1/
10
11
02
03
04
b0010 5
b01 6
b0000000000000000000000000000000000000000000000000000000000000000 7
b0000000000000000000000000000000000000000000000000000000000000000 9
b0000000000000000000000000000000000000000000000000000000000000000 ;
b0000000000000000000000000000000000000000000000000000000000000001 =
b0000000000000000000000000000000000000000000000000000000000000000 ?
b0000000000000000000000000000000000000000000000000000000000000000 A
1C
0D
b00000000 E
b0000000000000000000000000000000000000000000000000000000000000000 F
b0000000000000000000000000000000000000000000000000000000000000000 H
b0000000000000000000000000000000000000000000000000000000000000000 J
b0000000000000000000000000000000000000000000000000000000000000000 L
b0000000000000000000000000000000000000000000000000000000000000000 N
b0000000000000000000000000000000000000000000000000000000000000000 P
b0000000000000000000000000000000000000000000000000000000000000000 R
b0000000000000000000000000000000000000000000000000000000000000000 T
b0000000000000000000000000000000000000000000000000000000000000000 V
b0000000000000000000000000000000000000000000000000000000000000000 X
b0000000000000000000000000000000000000000000000000000000000000000 Z
b0000000000000000000000000000000000000000000000000000000000000000 \
b0000000000000000000000000000000000000000000000000000000000000000 ^
b0000000000000000000000000000000000000000000000000000000000000000 `
b0000000000000000000000000000000000000000000000000000000000000000 b
b0000000000000000000000000000000000000000000000000000000000000000 d
b0000000000000000000000000000000000000000000000000000000000000000 f
b0000000000000000000000000000000000000000000000000000000000000000 h
b0000000000000000000000000000000000000000000000000000000000000000 j
b0000000000000000000000000000000000000000000000000000000000000000 l
b0000000000000000000000000000000000000000000000000000000000000000 n
b0000000000000000000000000000000000000000000000000000000000000000 p
b0000000000000000000000000000000000000000000000000000000000000000 r
b0000000000000000000000000000000000000000000000000000000000000000 t
b0000000000000000000000000000000000000000000000000000000000000000 v
b0000000000000000000000000000000000000000000000000000000000000000 x
b0000000000000000000000000000000000000000000000000000000000000000 z
b0000000000000000000000000000000000000000000000000000000000000000 |
b0000000000000000000000000000000000000000000000000000000000000000 ~
b0000000000000000000000000000000000000000000000000000000000000000 "!
b0000000000000000000000000000000000000000000000000000000000000000 $!
b00000 &!
b0000000000000000000000000000000000000000000000000000000000000000 '!
0)!
b00010000000000001111101001 *!
b00 +!
b0000000000000000 ,!
1-!
b0000000000000000000000000000000000000000000000000000000000000000 .!
b0000000000000000000000000000000000000000000000000000000000000000 0!
b0000000000000000000000000000000000000000000000000000000000000001 2!
14!
b00000000000000000000000000010100 5!
b00000000000000000000000000101000 6!
#1
04!
#2
b0000000000000000000000000000000000000000000000000000000000000001 X
b01001 &!
b0000000000000000000000000000000000000000000000000000000000000001 '!
1)!
14!
#3
04!
#4
14!
#5
04!
#6
14!
#7
04!
#8
14!
#9
04!
#10
b0000000000000000000000000000000000000000000000000000000000001000 %
b11111000010000001000001111101010 '
b01010 (
b0000000000000000000000000000000000000000000000000000000000001000 ;
b0000000000000000000000000000000000000000000000000000000000001010 =
b0000000000000000000000000000000000000000000000000000000000001000 ?
b0000000000000000000000000000000000000000000000000000000000001000 A
0C
b00000001 E
b00010000001000001111101010 *!
0-!
b0000000000000000000000000000000000000000000000000000000000000100 0!
b0000000000000000000000000000000000000000000000000000000000001010 2!
14!
#11
04!
#12
b0000000000000000000000000000000000000000000000000000000000001100 %
b11111000010000010000001111101011 '
b01011 (
b00001 *
b00001 +
b0000000000000000000000000000000000000000000000000000000000010000 ;
b0000000000000000000000000000000000000000000000000000000000000101 =
b0000000000000000000000000000000000000000000000000000000000010000 ?
b0000000000000000000000000000000000000000000000000000000000010000 A
b00000010 E
b0000000000000000000000000000000000000000000000000000000000001010 Z
b01010 &!
b0000000000000000000000000000000000000000000000000000000000001010 '!
b00010000010000001111101011 *!
b0000000000000000000000000000000000000000000000000000000000001000 0!
b0000000000000000000000000000000000000000000000000000000000000101 2!
14!
#13
04!
#14
b0000000000000000000000000000000000000000000000000000000000010000 %
b11111000010000011000001111101100 '
b01100 (
b0000000000000000000000000000000000000000000000000000000000011000 ;
b0000111111111011111010100111110111101010110110111110111011111111 =
b0000000000000000000000000000000000000000000000000000000000011000 ?
b0000000000000000000000000000000000000000000000000000000000011000 A
b00000011 E
b0000000000000000000000000000000000000000000000000000000000000101 \
b01011 &!
b0000000000000000000000000000000000000000000000000000000000000101 '!
b00010000011000001111101100 *!
b0000000000000000000000000000000000000000000000000000000000001100 0!
b0000111111111011111010100111110111101010110110111110111011111111 2!
14!
#15
04!
#16
b0000000000000000000000000000000000000000000000000000000000010100 %
b11111000010000100000001111101101 '
b01101 (
b00010 *
b00010 +
b0000000000000000000000000000000000000000000000000000000000100000 ;
b0000000000000000000000000000000000000000000000000000000000000000 =
b0000000000000000000000000000000000000000000000000000000000100000 ?
b0000000000000000000000000000000000000000000000000000000000100000 A
b00000100 E
b0000111111111011111010100111110111101010110110111110111011111111 ^
b01100 &!
b0000111111111011111010100111110111101010110110111110111011111111 '!
b00010000100000001111101101 *!
b0000000000000000000000000000000000000000000000000000000000010000 0!
b0000000000000000000000000000000000000000000000000000000000000000 2!
14!
#17
04!
#18
b0000000000000000000000000000000000000000000000000000000000011000 %
b10101010000010110000000101001010 '
b01010 (
b01010 )
b01011 *
b01011 +
b10101010000 ,
0.
0/
01
b0001 5
b00 6
b0000000000000000000000000000000000000000000000000000000000001010 7
b0000000000000000000000000000000000000000000000000000000000000101 9
b0000000000000000000000000000000000000000000000000000000000001111 ;
b0000000000000000000000000000000000000000000000000000001011000000 ?
b0000000000000000000000000000000000000000000000000000000000000101 A
b00000001 E
b01101 &!
b0000000000000000000000000000000000000000000000000000000000000000 '!
b10000010110000000101001010 *!
b0000000000000000000000000000000000000000000000000000000000010100 0!
b0000000000000000000000000000000000000000000000000000000000001111 2!
14!
#19
04!
#20
b0000000000000000000000000000000000000000000000000000000000011100 %
b10001010000010100000000110001100 '
b01100 (
b01100 )
b01010 *
b01010 +
b10001010000 ,
b0000 5
b0000111111111011111010100111110111101010110110111110111011111111 7
b0000000000000000000000000000000000000000000000000000000000001111 9
b0000000000000000000000000000000000000000000000000000001010000000 ?
b0000000000000000000000000000000000000000000000000000000000001111 A
b0000000000000000000000000000000000000000000000000000000000001111 Z
b01010 &!
b0000000000000000000000000000000000000000000000000000000000001111 '!
b10000010100000000110001100 *!
b0000000000000000000000000000000000000000000000000000000000011000 0!
14!
#21
04!
#22
b0000000000000000000000000000000000000000000000000000000000100000 %
b10110100000000000000000010001100 '
b00100 )
b00000 *
b01100 +
b10110100000 ,
1-
00
13
b0111 5
b10 6
b0000000000000000000000000000000000000000000000000000000000000000 7
b0000000000000000000000000000000000000000000000000000000000010000 ?
b0000000000000000000000000000000000000000000000000000000000001111 ^
b01100 &!
b00000000000000000010001100 *!
b0000000000000000000000000000000000000000000000000000000000011100 0!
14!
#23
04!
#24
b0000000000000000000000000000000000000000000000000000000000100100 %
b10001011000010010000000110101101 '
b01101 (
b01101 )
b01001 *
b01001 +
b10001011000 ,
0-
10
03
b0010 5
b00 6
b0000000000000000000000000000000000000000000000000000000000000001 9
b0000000000000000000000000000000000000000000000000000000000000001 ;
b0000000000000000000000000000000000000000000000000000001001000000 ?
b0000000000000000000000000000000000000000000000000000000000000001 A
b00000000 E
0)!
b11000010010000000110101101 *!
b0000000000000000000000000000000000000000000000000000000000100000 0!
b0000000000000000000000000000000000000000000000000000000000000001 2!
14!
#25
04!
#26
b0000000000000000000000000000000000000000000000000000000000101000 %
b11001011000010010000000110001100 '
b01100 (
b01100 )
b11001011000 ,
b0110 5
b0000000000000000000000000000000000000000000000000000000000001111 7
b0000000000000000000000000000000000000000000000000000000000001110 ;
b00000001 E
b0000000000000000000000000000000000000000000000000000000000000001 `
b01101 &!
b0000000000000000000000000000000000000000000000000000000000000001 '!
1)!
b11000010010000000110001100 *!
b0000000000000000000000000000000000000000000000000000000000100100 0!
b0000000000000000000000000000000000000000000000000000000000001110 2!
14!
#27
04!
#28
b0000000000000000000000000000000000000000000000000000000000011100 %
b00010111111111111111111111111101 '
b11101 (
b11111 )
b11111 *
b11111 +
b00010111111 ,
00
14
b0000 5
b11 6
b0000000000000000000000000000000000000000000000000000000000000000 7
b0000000000000000000000000000000000000000000000000000000000000000 9
b0000000000000000000000000000000000000000000000000000000000000000 ;
b1111111111111111111111111111111111111111111111111111111111110100 ?
b0000000000000000000000000000000000000000000000000000000000000000 A
1C
b00000000 E
b0000000000000000000000000000000000000000000000000000000000001110 ^
b01100 &!
b0000000000000000000000000000000000000000000000000000000000001110 '!
b11111111111111111111111101 *!
b0000000000000000000000000000000000000000000000000000000000101000 0!
b0000000000000000000000000000000000000000000000000000000000000000 2!
14!
#29
04!
